{"data":[{"category":"Computers\/technology","name":"Technology for Seniors Made Easy","id":"641097519240687","created_time":"2013-04-10T10:14:19+0000"},{"category":"Public figure","name":"Robin Korth","id":"504093259627567","created_time":"2013-04-03T19:07:03+0000"},{"category":"Restaurant\/cafe","category_list":[{"id":"139141179489281","name":"Boating"},{"id":"110107385737667","name":"New American Restaurant"}],"name":"Kaluz","id":"556865191006588","created_time":"2013-03-31T09:24:48+0000"},{"category":"Business person","name":"John & Tricia Puritz: Regional Vice President, Primerica","id":"449717655109583","created_time":"2013-03-23T16:37:37+0000"},{"category":"Non-profit organization","name":"Dancing with the Stars of Broward","id":"104989232958185","created_time":"2013-03-06T19:08:01+0000"},{"category":"Real estate","category_list":[{"id":"198327773511962","name":"Real Estate"}],"name":"Miami Real Estate Report","id":"271522189529742","created_time":"2013-03-05T20:08:05+0000"},{"category":"Personal blog","name":"Jessica Bari","id":"501938523195603","created_time":"2013-02-28T17:06:54+0000"},{"category":"Event planning\/event services","name":"Events by Vento Designs","id":"272217214118","created_time":"2013-02-17T23:55:18+0000"},{"category":"Local business","category_list":[{"id":"132003726865268","name":"Pediatrics"},{"id":"114047665342448","name":"Financial Aid"}],"name":"Jessica June Children's Cancer Foundation","id":"213559845332261","created_time":"2013-02-17T23:54:50+0000"},{"category":"Church\/religious organization","category_list":[{"id":"187714557925874","name":"Religious Organization"}],"name":"Metaphysical Chapel of South Florida","id":"211482725554111","created_time":"2013-02-13T03:21:57+0000"},{"category":"Spas\/beauty\/personal care","category_list":[{"id":"139225689474222","name":"Spa, Beauty & Personal Care"},{"id":"145118935550090","name":"Medical & Health"}],"name":"Essential Day Spa & Wellness Institute","id":"110508525698155","created_time":"2013-01-28T17:06:47+0000"},{"category":"Public figure","name":"Thomas John: Psychic Medium, Clairvoyant, and Published Author.","id":"193434870723741","created_time":"2013-01-23T02:09:08+0000"},{"category":"Local business","category_list":[{"id":"2500","name":"Local Business"}],"name":"Aralim - Psychic Advisors","id":"229825240386985","created_time":"2013-01-17T14:43:32+0000"},{"category":"Professional services","category_list":[{"id":"180001142041484","name":"Wills & Estate Lawyer"},{"id":"121688031239297","name":"Estate Lawyer"}],"name":"Wild Felice & Partners, P.A.","id":"212641902287","created_time":"2013-01-16T23:50:32+0000"},{"category":"Non-profit organization","category_list":[{"id":"151676848220295","name":"Education"},{"id":"226326230802065","name":"Charity Organization"},{"id":"211155112228091","name":"Event Venue"}],"name":"JA World Uncorked","id":"395970723825713","created_time":"2013-01-14T00:44:36+0000"},{"category":"Local business","name":"Kissinger Promotions","id":"70210869015","created_time":"2013-01-08T04:11:32+0000"},{"category":"Organization","name":"Inspiration University- inspiring women to be their best","id":"105329332843582","created_time":"2012-12-29T14:42:31+0000"},{"category":"Pet services","category_list":[{"id":"188573091164316","name":"Pet Store"},{"id":"188031587886173","name":"Jewelry Store"}],"name":"Diamonds and Doggies","id":"107159656047580","created_time":"2012-12-24T20:09:06+0000"},{"category":"Local business","category_list":[{"id":"2500","name":"Local Business"}],"name":"South Florida Social","id":"160840960626229","created_time":"2012-12-22T15:19:45+0000"},{"category":"Musician\/band","name":"Jessica Dansediva","id":"252632284865541","created_time":"2012-12-12T03:38:00+0000"},{"category":"Bar","category_list":[{"id":"135930436481618","name":"Lounge"},{"id":"192661127431931","name":"Wine Bar"}],"name":"Preston\u2019s Wine & Martini Lounge","id":"119115764829318","created_time":"2012-12-10T16:54:05+0000"},{"category":"Magazine","category_list":[{"id":"1307","name":"Magazine"}],"name":"Go Riverwalk Fort Lauderdale","id":"129538143809216","created_time":"2012-12-08T19:12:44+0000"},{"category":"Spas\/beauty\/personal care","category_list":[{"id":"139225689474222","name":"Spa, Beauty & Personal Care"}],"name":"PazazzBodyWork","id":"322720591131204","created_time":"2012-12-07T20:12:27+0000"},{"category":"Media\/news\/publishing","category_list":[{"id":"2233","name":"Media\/News\/Publishing"}],"name":"TravelhostFTL","id":"119499508114475","created_time":"2012-12-06T23:05:25+0000"},{"category":"Local business","category_list":[{"id":"179672275401610","name":"Business Consultant"},{"id":"357645644269220","name":"Alternative & Holistic Health"},{"id":"185900881450649","name":"Personal Coaching"}],"name":"Thrive Any Way Personal and Business Coaching","id":"117510798412210","created_time":"2012-12-01T01:49:25+0000"},{"category":"Public figure","name":"Aria Blake","id":"376877975736498","created_time":"2012-11-30T21:12:25+0000"},{"category":"Local business","category_list":[{"id":"145118935550090","name":"Medical & Health"}],"name":"A Better Back Lumbar Support Pillow","id":"120015559577","created_time":"2012-11-30T16:39:51+0000"},{"category":"Website","name":"Dorit \"The Connector\"","id":"271199989658933","created_time":"2012-11-29T20:07:53+0000"},{"category":"Author","name":"Kristin Mackey (KMack)","id":"141288802603844","created_time":"2012-11-29T16:58:35+0000"},{"category":"Cause","category_list":[{"id":"226326230802065","name":"Charity Organization"},{"id":"187751327923426","name":"Educational Organization"}],"name":"Circle of Wise Women \u0040JA South Florida","id":"115839011799617","created_time":"2012-11-27T21:34:52+0000"},{"category":"Non-profit organization","category_list":[{"id":"192119584190796","name":"Event"}],"name":"Winterfest Boat Parade","id":"192877404081437","created_time":"2012-11-26T21:11:34+0000"},{"category":"Pet supplies","name":"Good Dog Bakery","id":"105766730920","created_time":"2012-11-15T17:22:57+0000"},{"category":"Automotive","name":"BOCA AUTO Service","id":"233786093322560","created_time":"2012-11-15T13:35:23+0000"},{"category":"Consulting\/business services","category_list":[{"id":"2248","name":"Consulting\/Business Services"}],"name":"Mister Nonprofit Consultancy, Inc.","id":"124041274323576","created_time":"2012-11-12T19:37:09+0000"},{"category":"Food\/beverages","category_list":[{"id":"139433292785470","name":"Caterer"},{"id":"182269951819423","name":"Cooking Lesson"}],"name":"Lenore Nolan-Ryan Cooking School & Catering","id":"75412556782","created_time":"2012-11-10T15:26:33+0000"},{"category":"Professional services","category_list":[{"id":"191681657527859","name":"Fitness Center"},{"id":"181045748599578","name":"Personal Trainer"}],"name":"Physical Revolution","id":"116861515038117","created_time":"2012-11-09T21:52:38+0000"},{"category":"Non-profit organization","category_list":[{"id":"2603","name":"Non-Profit Organization"}],"name":"Can\u2019t Stomach Cancer","id":"319847357935","created_time":"2012-11-09T13:07:34+0000"},{"category":"Health\/beauty","name":"LA Fitness","id":"135669809790671","created_time":"2012-10-31T23:53:45+0000"},{"category":"Public figure","name":"Adriana de Moura","id":"432646060128462","created_time":"2012-10-27T15:41:13+0000"},{"category":"Lawyer","category_list":[{"id":"1607","name":"Lawyer"}],"name":"John P. Contini","id":"136758936374824","created_time":"2012-10-26T21:50:22+0000"},{"category":"Health\/medical\/pharmacy","category_list":[{"id":"145118935550090","name":"Medical & Health"}],"name":"Pearl White Dentistry","id":"124109370991610","created_time":"2012-10-22T16:29:38+0000"},{"category":"Public figure","name":"Rumi Quotes","id":"145479798858810","created_time":"2012-10-20T02:01:04+0000"},{"category":"Community","name":"Fort Lauderdale Sole Sisters","id":"149129291765748","created_time":"2012-10-19T18:55:41+0000"},{"category":"Magazine","name":"Lifestyle Magazines","id":"190986924245760","created_time":"2012-10-19T18:52:42+0000"},{"category":"Public figure","name":"Val Silidker","id":"508245262520302","created_time":"2012-10-15T19:26:58+0000"},{"category":"Personal blog","name":"LaurenFromTheLeft","id":"365003280247981","created_time":"2012-10-15T19:26:16+0000"},{"category":"Company","name":"Sano seafoods","id":"111232722236817","created_time":"2012-10-11T00:07:48+0000"},{"category":"Home improvement","category_list":[{"id":"108427109235243","name":"Home Improvement"}],"name":"T-Square Construction & Services, LLC","id":"123579317724241","created_time":"2012-10-03T02:00:53+0000"},{"category":"Artist","name":"Blair Photography","id":"154856557887212","created_time":"2012-09-22T19:30:08+0000"},{"category":"Non-profit organization","category_list":[{"id":"198327773511962","name":"Real Estate"}],"name":"Broward Council of the Miami Association of Realtors","id":"154348031311104","created_time":"2012-09-21T20:52:16+0000"},{"category":"Health\/medical\/pharmacy","category_list":[{"id":"192781160749720","name":"Chiropractor"}],"name":"Dr. Matthew C. Supran","id":"171663999558184","created_time":"2012-09-17T18:21:41+0000"},{"category":"Company","category_list":[{"id":"2200","name":"Company"}],"name":"S.MARK Graphics","id":"196842050367612","created_time":"2012-09-17T17:54:06+0000"},{"category":"Transport\/freight","category_list":[{"id":"152367304818850","name":"Transportation Service"},{"id":"184395321600410","name":"Cargo & Freight"}],"name":"A-Pronto Delivery Service","id":"251999654729","created_time":"2012-09-07T20:58:59+0000"},{"category":"Community organization","name":"Downtown Fort Lauderdale","id":"249895398440467","created_time":"2012-08-28T03:21:29+0000"},{"category":"Attractions\/things to do","name":"LastMinute Lauderdale","id":"152219468138352","created_time":"2012-08-27T17:30:19+0000"},{"category":"Professional services","name":"Redhead Marketing, Inc.","id":"190512777659313","created_time":"2012-08-23T14:42:06+0000"},{"category":"Non-profit organization","name":"BNI Premier of Fort Lauderdale","id":"241296020539","created_time":"2012-08-18T11:42:24+0000"},{"category":"Website","category_list":[{"id":"2202","name":"Website"}],"name":"E-Miles","id":"160079844040708","created_time":"2012-08-17T21:40:32+0000"},{"category":"Public places","category_list":[{"id":"2522","name":"Public Places"}],"name":"FtLauderdaleSun","id":"123705180987485","created_time":"2012-07-31T02:32:39+0000"},{"category":"Education","category_list":[{"id":"151676848220295","name":"Education"}],"name":"Simple Results","id":"184649088944","created_time":"2012-07-31T02:32:06+0000"},{"category":"Local business","category_list":[{"id":"2500","name":"Local Business"}],"name":"Timeless Beauty","id":"225107704249487","created_time":"2012-07-26T17:47:52+0000"},{"category":"Author","name":"Maya Angelou","id":"33512954795","created_time":"2012-07-15T21:16:45+0000"},{"category":"Local business","category_list":[{"id":"152880021441864","name":"Community Organization"}],"name":"Greater Fort Lauderdale Chamber of Commerce","id":"117431268341228","created_time":"2012-07-15T16:12:23+0000"},{"category":"Arts\/entertainment\/nightlife","category_list":[{"id":"133436743388217","name":"Arts & Entertainment"}],"name":"Studio 19 Fine Art","id":"217634305596","created_time":"2012-07-15T15:37:25+0000"},{"category":"Professional services","category_list":[{"id":"176831012360626","name":"Professional Services"}],"name":"Suzanne Barton Photography","id":"205866526178959","created_time":"2012-07-10T01:51:36+0000"},{"category":"Health\/beauty","name":"Timeless Beauty Aesthetics","id":"239023912863966","created_time":"2012-07-07T12:28:35+0000"},{"category":"Public figure","category_list":[{"id":"357645644269220","name":"Alternative & Holistic Health"},{"id":"108565442553819","name":"Psychic"}],"name":"Official Edgar Cayce Page","id":"373975233784","created_time":"2012-07-01T17:00:32+0000"},{"category":"School","name":"Johane Rutledge School of Intuition","id":"232856750165337","created_time":"2012-07-01T16:59:24+0000"},{"category":"Professional services","category_list":[{"id":"176831012360626","name":"Professional Services"}],"name":"Tiers of Healing","id":"410771112294767","created_time":"2012-06-29T17:07:20+0000"},{"category":"Government official","category_list":[{"id":"1701","name":"Government Official"}],"name":"Rep. Debbie Wasserman Schultz","id":"88904724121","created_time":"2012-06-29T17:03:06+0000"},{"category":"Public figure","name":"Ellen Degeneres","id":"36772172240","created_time":"2012-06-26T01:15:19+0000"},{"category":"Public figure","name":"Marianne Williamson","id":"207697880579","created_time":"2012-06-26T01:15:13+0000"},{"category":"Professional services","category_list":[{"id":"176831012360626","name":"Professional Services"}],"name":"Laurina The Energy Shifter","id":"403252316392067","created_time":"2012-06-21T21:14:46+0000"},{"category":"Consulting\/business services","category_list":[{"id":"179672275401610","name":"Business Consultant"}],"name":"QuinnProQuo","id":"10150119168630375","created_time":"2012-06-20T23:19:34+0000"},{"category":"Health\/beauty","name":"Coach C's Get Healthy","id":"223492001052146","created_time":"2012-06-20T21:25:16+0000"},{"category":"Local business","category_list":[{"id":"162914327091136","name":"Travel Agency"}],"name":"World Cruises & Travel","id":"258241244210956","created_time":"2012-06-14T18:41:53+0000"},{"category":"Non-profit organization","name":"PACE Center for Girls Inc","id":"133617825555","created_time":"2012-06-12T02:25:15+0000"},{"category":"Local business","category_list":[{"id":"199182823425834","name":"Electrician"}],"name":"Mister Sparky Pompano Beach","id":"320850090544","created_time":"2012-06-11T17:59:49+0000"},{"category":"Community","name":"PWS Concepts - Maximize Your Social Media","id":"394918650561061","created_time":"2012-06-09T20:57:29+0000"},{"category":"Health\/medical\/pharmacy","category_list":[{"id":"174187662626299","name":"Dentist"}],"name":"The Tamarac Dentist","id":"100387730065494","created_time":"2012-06-06T20:05:25+0000"},{"category":"Musician\/band","name":"Official Amy Barbera Fan Page","id":"282129867979","created_time":"2012-06-05T16:46:36+0000"}],"paging":{"next":"https:\/\/graph.facebook.com\/100003889458829\/likes?access_token=AAACEdEose0cBAMYosNuQgnCMBhgO4meNR3qH1cjXNhenSu6GRD6HiTa20OCYdbn297Lf2pZALjodgovOYrfZB0K5KvL0ONYoSHKuOldxmnwN01tZBh8&limit=5000&offset=5000&__after_id=282129867979"}}