{"data":[{"id":"148653331973594","from":{"name":"Risshi Trivedi","id":"100004867833259"},"name":"Effect Mania\r\n\r\n\u2665\u2665\u2665Hey guys, Download the Effect Mania and Enjoy with your photo effect. And You have never seen that type of effect in any apps. And Please give good review to dis app...\u2665\u2665\u2665\r\n\r\nhttps:\/\/play.google.com\/store\/apps\/details?id=com.shine.effectmania","picture":"https:\/\/fbcdn-photos-b-a.akamaihd.net\/hphotos-ak-prn1\/155712_148653331973594_1110120014_s.jpg","source":"https:\/\/fbcdn-sphotos-b-a.akamaihd.net\/hphotos-ak-prn1\/s720x720\/155712_148653331973594_1110120014_n.jpg","height":351,"width":720,"images":[{"height":500,"width":1024,"source":"https:\/\/fbcdn-sphotos-b-a.akamaihd.net\/hphotos-ak-prn1\/905295_148653331973594_1110120014_o.jpg"},{"height":468,"width":960,"source":"https:\/\/fbcdn-sphotos-b-a.akamaihd.net\/hphotos-ak-prn1\/155712_148653331973594_1110120014_n.jpg"},{"height":351,"width":720,"source":"https:\/\/fbcdn-sphotos-b-a.akamaihd.net\/hphotos-ak-prn1\/s720x720\/155712_148653331973594_1110120014_n.jpg"},{"height":292,"width":600,"source":"https:\/\/fbcdn-sphotos-b-a.akamaihd.net\/hphotos-ak-prn1\/s600x600\/155712_148653331973594_1110120014_n.jpg"},{"height":234,"width":480,"source":"https:\/\/fbcdn-sphotos-b-a.akamaihd.net\/hphotos-ak-prn1\/s480x480\/155712_148653331973594_1110120014_n.jpg"},{"height":156,"width":320,"source":"https:\/\/fbcdn-sphotos-b-a.akamaihd.net\/hphotos-ak-prn1\/s320x320\/155712_148653331973594_1110120014_n.jpg"},{"height":87,"width":180,"source":"https:\/\/fbcdn-photos-b-a.akamaihd.net\/hphotos-ak-prn1\/155712_148653331973594_1110120014_a.jpg"},{"height":63,"width":130,"source":"https:\/\/fbcdn-photos-b-a.akamaihd.net\/hphotos-ak-prn1\/155712_148653331973594_1110120014_s.jpg"},{"height":63,"width":130,"source":"https:\/\/fbcdn-photos-b-a.akamaihd.net\/hphotos-ak-prn1\/s75x225\/155712_148653331973594_1110120014_s.jpg"}],"link":"http:\/\/www.facebook.com\/photo.php?fbid=148653331973594&set=p.148653331973594&type=1","icon":"https:\/\/fbstatic-a.akamaihd.net\/rsrc.php\/v2\/yz\/r\/StEh3RhPvjk.gif","created_time":"2013-04-15T13:17:51+0000","updated_time":"2013-04-15T13:17:58+0000","likes":{"data":[{"id":"100002952786781","name":"Florin Iordan Romica"},{"id":"100004398463198","name":"Romeo Dinca"},{"id":"100005403511868","name":"Elio Avukati Elio Avukati"},{"id":"100003355429650","name":"Anna Anyta"},{"id":"100004867833259","name":"Risshi Trivedi"}],"paging":{"next":"https:\/\/graph.facebook.com\/148653331973594\/likes?access_token=AAACEdEose0cBAMYosNuQgnCMBhgO4meNR3qH1cjXNhenSu6GRD6HiTa20OCYdbn297Lf2pZALjodgovOYrfZB0K5KvL0ONYoSHKuOldxmnwN01tZBh8&limit=25&offset=25&__after_id=100004867833259"}}},{"id":"318777494914915","from":{"name":"Tyler Nicholas Bangs","id":"100003480004900"},"name":"y so serious.....ahahahahhahahahahha ....so who's up for the party???? \\m\/","picture":"https:\/\/fbcdn-photos-c-a.akamaihd.net\/hphotos-ak-prn1\/563738_318777494914915_1765409354_s.jpg","source":"https:\/\/fbcdn-sphotos-c-a.akamaihd.net\/hphotos-ak-prn1\/563738_318777494914915_1765409354_n.jpg","height":333,"width":211,"images":[{"height":333,"width":211,"source":"https:\/\/fbcdn-sphotos-c-a.akamaihd.net\/hphotos-ak-prn1\/563738_318777494914915_1765409354_n.jpg"},{"height":333,"width":211,"source":"https:\/\/fbcdn-sphotos-c-a.akamaihd.net\/hphotos-ak-prn1\/563738_318777494914915_1765409354_n.jpg"},{"height":320,"width":202,"source":"https:\/\/fbcdn-sphotos-c-a.akamaihd.net\/hphotos-ak-prn1\/s320x320\/563738_318777494914915_1765409354_n.jpg"},{"height":284,"width":180,"source":"https:\/\/fbcdn-photos-c-a.akamaihd.net\/hphotos-ak-prn1\/563738_318777494914915_1765409354_a.jpg"},{"height":130,"width":82,"source":"https:\/\/fbcdn-photos-c-a.akamaihd.net\/hphotos-ak-prn1\/563738_318777494914915_1765409354_s.jpg"},{"height":130,"width":82,"source":"https:\/\/fbcdn-photos-c-a.akamaihd.net\/hphotos-ak-prn1\/s75x225\/563738_318777494914915_1765409354_s.jpg"}],"link":"http:\/\/www.facebook.com\/photo.php?fbid=318777494914915&set=p.318777494914915&type=1","icon":"https:\/\/fbstatic-a.akamaihd.net\/rsrc.php\/v2\/yz\/r\/StEh3RhPvjk.gif","created_time":"2013-04-15T08:44:58+0000","updated_time":"2013-04-15T09:02:25+0000","comments":{"data":[{"id":"318777494914915_680834","from":{"name":"Sadik Al Sary","id":"100001104133336"},"message":"no      good","can_remove":false,"created_time":"2013-04-15T08:59:17+0000","like_count":0,"user_likes":false},{"id":"318777494914915_681851","from":{"name":"Curtis Kuykendall","id":"100004516264169"},"message":"Let`s go","can_remove":false,"created_time":"2013-04-15T22:21:46+0000","like_count":0,"user_likes":false}],"paging":{"cursors":{"after":"Mg==","before":"MQ=="},"next":"https:\/\/graph.facebook.com\/318777494914915\/comments?access_token=AAACEdEose0cBAMYosNuQgnCMBhgO4meNR3qH1cjXNhenSu6GRD6HiTa20OCYdbn297Lf2pZALjodgovOYrfZB0K5KvL0ONYoSHKuOldxmnwN01tZBh8&limit=25&after=Mg\u00253D\u00253D"}},"likes":{"data":[{"id":"100005037638722","name":"Rleon Leon"},{"id":"100001639732849","name":"Jose Hernandez"},{"id":"100005272680711","name":"Yansel M\u00e1s"},{"id":"100004472169549","name":"Antoine Yaech Chao"},{"id":"100003681607451","name":"Jorge Mauras Alvarado"},{"id":"100002559276326","name":"Vladimir Albert Cerna Maza"},{"id":"100001009344251","name":"Christopher Barnett"},{"id":"100004382437398","name":"Richard Sztajer"},{"id":"100003690349590","name":"Peewee Mesa"},{"id":"100005475841630","name":"Wilfred Perez"}],"paging":{"next":"https:\/\/graph.facebook.com\/318777494914915\/likes?access_token=AAACEdEose0cBAMYosNuQgnCMBhgO4meNR3qH1cjXNhenSu6GRD6HiTa20OCYdbn297Lf2pZALjodgovOYrfZB0K5KvL0ONYoSHKuOldxmnwN01tZBh8&limit=25&offset=25&__after_id=100005475841630"}}},{"id":"504761962893425","from":{"id":"471991986170423","category":"Community","name":"Life is once"},"name":"Fahad Arshad","name_tags":[[{"id":"100001775196618","name":"Fahad Arshad","type":"user","offset":0,"length":12}]],"picture":"https:\/\/fbcdn-photos-a.akamaihd.net\/hphotos-ak-prn1\/59764_504761962893425_851166866_s.jpg","source":"https:\/\/fbcdn-sphotos-b-a.akamaihd.net\/hphotos-ak-prn1\/59764_504761962893425_851166866_n.jpg","height":403,"width":403,"images":[{"height":403,"width":403,"source":"https:\/\/fbcdn-sphotos-b-a.akamaihd.net\/hphotos-ak-prn1\/59764_504761962893425_851166866_n.jpg"},{"height":403,"width":403,"source":"https:\/\/fbcdn-sphotos-b-a.akamaihd.net\/hphotos-ak-prn1\/59764_504761962893425_851166866_n.jpg"},{"height":320,"width":320,"source":"https:\/\/fbcdn-sphotos-b-a.akamaihd.net\/hphotos-ak-prn1\/s320x320\/59764_504761962893425_851166866_n.jpg"},{"height":180,"width":180,"source":"https:\/\/fbcdn-photos-a.akamaihd.net\/hphotos-ak-prn1\/59764_504761962893425_851166866_a.jpg"},{"height":130,"width":130,"source":"https:\/\/fbcdn-photos-a.akamaihd.net\/hphotos-ak-prn1\/59764_504761962893425_851166866_s.jpg"},{"height":130,"width":130,"source":"https:\/\/fbcdn-photos-a.akamaihd.net\/hphotos-ak-prn1\/s75x225\/59764_504761962893425_851166866_s.jpg"}],"link":"http:\/\/www.facebook.com\/photo.php?fbid=504761962893425&set=a.489858444383777.104821.471991986170423&type=1","icon":"https:\/\/fbstatic-a.akamaihd.net\/rsrc.php\/v2\/yz\/r\/StEh3RhPvjk.gif","created_time":"2013-04-05T15:15:24+0000","updated_time":"2013-04-05T15:15:24+0000","tags":{"data":[{"id":"100003375834845","name":"Elizabet Palacios Sanchez","x":67.245657568238,"y":20.595533498759,"created_time":"2013-04-12T12:09:01+0000"},{"id":"100000675064869","name":"Sandra Elizabeth Espinoza Rojas","x":45.409429280397,"y":18.610421836228,"created_time":"2013-04-12T12:09:00+0000"},{"id":"100005469155120","name":"Michele Albuquerque","x":65.260545905707,"y":12.655086848635,"created_time":"2013-04-12T12:08:55+0000"},{"id":"100005440904043","name":"Alis Morales","x":50.372208436725,"y":30.521091811414,"created_time":"2013-04-12T12:08:52+0000"},{"id":"100005347723581","name":"Acha Tasya","x":82.87841191067,"y":17.617866004963,"created_time":"2013-04-12T12:08:50+0000"},{"id":"100005362032178","name":"Martha Allen","x":47.890818858561,"y":16.625310173697,"created_time":"2013-04-12T12:08:49+0000"},{"id":"100003301121720","name":"Assmae Bar\u00e7a Bell","x":71.464019851117,"y":13.399503722084,"created_time":"2013-04-12T12:08:47+0000"},{"id":"100005184759779","name":"Alex Hyde Sobe","x":44.168734491315,"y":12.406947890819,"created_time":"2013-04-12T12:08:45+0000"},{"id":"100004055085927","name":"Thaynara Alessandra","x":74.193548387097,"y":9.181141439206,"created_time":"2013-04-12T12:08:44+0000"},{"id":"100005577452693","name":"Adri Adriana","x":32.258064516129,"y":8.4367245657568,"created_time":"2013-04-12T12:08:42+0000"},{"id":"100005531322288","name":"Arman Khan","x":70.223325062035,"y":17.866004962779,"created_time":"2013-04-12T12:08:41+0000"},{"id":"100002814591581","name":"Sailyn Ana Broze","x":21.836228287841,"y":10.173697270471,"created_time":"2013-04-12T12:08:38+0000"},{"id":"100005537022744","name":"Ana Paula Lucena","x":60.29776674938,"y":23.821339950372,"created_time":"2013-04-12T12:08:37+0000"},{"id":"100005229122650","name":"Ana Santos","x":67.245657568238,"y":32.009925558313,"created_time":"2013-04-12T12:08:32+0000"},{"id":"100003360533402","name":"Nathalia Natha","x":45.161290322581,"y":33.746898263027,"created_time":"2013-04-12T12:08:30+0000"},{"id":"100002747760271","name":"Jebali Rihab","x":51.116625310174,"y":7.9404466501241,"created_time":"2013-04-12T12:08:27+0000"}],"paging":{"next":"https:\/\/graph.facebook.com\/504761962893425\/tags?access_token=AAACEdEose0cBAMYosNuQgnCMBhgO4meNR3qH1cjXNhenSu6GRD6HiTa20OCYdbn297Lf2pZALjodgovOYrfZB0K5KvL0ONYoSHKuOldxmnwN01tZBh8&limit=5000&offset=5000&__after_id=100002747760271"}},"likes":{"data":[{"id":"100003191443889","name":"Goila Sandu Fericel-Rominski Chirtzescu"},{"id":"100005469155120","name":"Michele Albuquerque"},{"id":"100005564460630","name":"Ricardo Amaral"},{"id":"100005155903489","name":"Glend Tingon"},{"id":"1007321089","name":"Niko Santos"},{"id":"100000390220344","name":"John Fox"},{"id":"100001764896373","name":"Walman Flores"},{"id":"100001355040750","name":"Echang Chuters"},{"id":"100001040282119","name":"Cristina Fofiu"},{"id":"100001860082840","name":"Paul Anton"},{"id":"100005524473859","name":"Yang Yu Lee Kelly"},{"id":"100004242433095","name":"Randy Medina"}],"paging":{"next":"https:\/\/graph.facebook.com\/504761962893425\/likes?access_token=AAACEdEose0cBAMYosNuQgnCMBhgO4meNR3qH1cjXNhenSu6GRD6HiTa20OCYdbn297Lf2pZALjodgovOYrfZB0K5KvL0ONYoSHKuOldxmnwN01tZBh8&limit=25&offset=25&__after_id=100004242433095"}}},{"id":"353232894796615","from":{"id":"126739787445928","category":"Arts\/entertainment\/nightlife","name":"Hyde Beach Miami"},"name":"Franz Mahr","picture":"https:\/\/fbcdn-photos-h-a.akamaihd.net\/hphotos-ak-snc6\/224749_353232894796615_240939507_s.jpg","source":"https:\/\/fbcdn-sphotos-h-a.akamaihd.net\/hphotos-ak-snc6\/s720x720\/224749_353232894796615_240939507_n.jpg","height":480,"width":720,"images":[{"height":1366,"width":2048,"source":"https:\/\/fbcdn-sphotos-h-a.akamaihd.net\/hphotos-ak-ash3\/882843_353232894796615_240939507_o.jpg"},{"height":640,"width":960,"source":"https:\/\/fbcdn-sphotos-h-a.akamaihd.net\/hphotos-ak-snc6\/224749_353232894796615_240939507_n.jpg"},{"height":480,"width":720,"source":"https:\/\/fbcdn-sphotos-h-a.akamaihd.net\/hphotos-ak-snc6\/s720x720\/224749_353232894796615_240939507_n.jpg"},{"height":400,"width":600,"source":"https:\/\/fbcdn-sphotos-h-a.akamaihd.net\/hphotos-ak-snc6\/s600x600\/224749_353232894796615_240939507_n.jpg"},{"height":320,"width":480,"source":"https:\/\/fbcdn-sphotos-h-a.akamaihd.net\/hphotos-ak-snc6\/s480x480\/224749_353232894796615_240939507_n.jpg"},{"height":213,"width":320,"source":"https:\/\/fbcdn-sphotos-h-a.akamaihd.net\/hphotos-ak-snc6\/s320x320\/224749_353232894796615_240939507_n.jpg"},{"height":120,"width":180,"source":"https:\/\/fbcdn-photos-h-a.akamaihd.net\/hphotos-ak-snc6\/224749_353232894796615_240939507_a.jpg"},{"height":86,"width":130,"source":"https:\/\/fbcdn-photos-h-a.akamaihd.net\/hphotos-ak-snc6\/224749_353232894796615_240939507_s.jpg"},{"height":86,"width":130,"source":"https:\/\/fbcdn-photos-h-a.akamaihd.net\/hphotos-ak-snc6\/s75x225\/224749_353232894796615_240939507_s.jpg"}],"link":"http:\/\/www.facebook.com\/photo.php?fbid=353232894796615&set=a.353230294796875.1073741830.126739787445928&type=1","icon":"https:\/\/fbstatic-a.akamaihd.net\/rsrc.php\/v2\/yz\/r\/StEh3RhPvjk.gif","place":{"id":"126739787445928","name":"Hyde Beach Miami","location":{"street":"","city":"Miami Beach","state":"FL","country":"United States","zip":"","latitude":25.792478735761,"longitude":-80.128133376345}},"created_time":"2013-03-21T21:28:39+0000","updated_time":"2013-03-21T21:30:19+0000","tags":{"data":[{"id":"100005184759779","name":"Alex Hyde Sobe","x":73.472222222222,"y":45,"created_time":"2013-03-29T00:23:31+0000"},{"id":"56302476","name":"Francisco Cabrera","x":20.069444444444,"y":68.166666666667,"created_time":"2013-03-25T03:23:49+0000"}],"paging":{"next":"https:\/\/graph.facebook.com\/353232894796615\/tags?access_token=AAACEdEose0cBAMYosNuQgnCMBhgO4meNR3qH1cjXNhenSu6GRD6HiTa20OCYdbn297Lf2pZALjodgovOYrfZB0K5KvL0ONYoSHKuOldxmnwN01tZBh8&limit=5000&offset=5000&__after_id=56302476"}},"comments":{"data":[{"id":"353232894796615_776937","from":{"name":"Daniel Justin Greeneyesz Hernandez","id":"100000154472914"},"message":"Thats ma homie lol","can_remove":false,"created_time":"2013-03-25T01:11:23+0000","like_count":0,"user_likes":false},{"id":"353232894796615_777410","from":{"name":"Francisco Cabrera","id":"56302476"},"message":"TRUEEEEEEEEEE!!!!!!!!!","can_remove":false,"created_time":"2013-03-25T07:18:39+0000","like_count":0,"user_likes":false}],"paging":{"cursors":{"after":"Mg==","before":"MQ=="},"next":"https:\/\/graph.facebook.com\/353232894796615\/comments?access_token=AAACEdEose0cBAMYosNuQgnCMBhgO4meNR3qH1cjXNhenSu6GRD6HiTa20OCYdbn297Lf2pZALjodgovOYrfZB0K5KvL0ONYoSHKuOldxmnwN01tZBh8&limit=25&after=Mg\u00253D\u00253D"}},"likes":{"data":[{"id":"100000090523894","name":"Teodik Markarian"},{"id":"100002761773221","name":"Hatam Zolfaghari"},{"id":"1360841036","name":"Roberto Santamarina"},{"id":"100002586383708","name":"Genaro Ibarra"},{"id":"100000797003432","name":"Mark Jones"},{"id":"100004036384426","name":"Nemo Alizadeh"},{"id":"100005358431922","name":"Myint Aung"},{"id":"100004054035390","name":"Star Speed"},{"id":"100004942535842","name":"Gaston Ale Novara"},{"id":"100005078229824","name":"Eric Vance Cabling"},{"id":"1545390718","name":"Juan JR Rosado"},{"id":"100004035405235","name":"Kevin Cabrera"},{"id":"1234351718","name":"Ari Arias"},{"id":"100000154472914","name":"Daniel Justin Greeneyesz Hernandez"},{"id":"1062189039","name":"Jp Betancur"}],"paging":{"next":"https:\/\/graph.facebook.com\/353232894796615\/likes?access_token=AAACEdEose0cBAMYosNuQgnCMBhgO4meNR3qH1cjXNhenSu6GRD6HiTa20OCYdbn297Lf2pZALjodgovOYrfZB0K5KvL0ONYoSHKuOldxmnwN01tZBh8&limit=25&offset=25&__after_id=1062189039"}}},{"id":"421104927976817","from":{"name":"Bhatt Suraj","id":"100002319395286"},"name":"frds......","picture":"https:\/\/fbcdn-photos-d-a.akamaihd.net\/hphotos-ak-snc7\/392793_421104927976817_27125352_s.jpg","source":"https:\/\/fbcdn-sphotos-d-a.akamaihd.net\/hphotos-ak-snc7\/392793_421104927976817_27125352_n.jpg","height":428,"width":400,"images":[{"height":428,"width":400,"source":"https:\/\/fbcdn-sphotos-d-a.akamaihd.net\/hphotos-ak-snc7\/392793_421104927976817_27125352_n.jpg"},{"height":428,"width":400,"source":"https:\/\/fbcdn-sphotos-d-a.akamaihd.net\/hphotos-ak-snc7\/392793_421104927976817_27125352_n.jpg"},{"height":320,"width":299,"source":"https:\/\/fbcdn-sphotos-d-a.akamaihd.net\/hphotos-ak-snc7\/s320x320\/392793_421104927976817_27125352_n.jpg"},{"height":192,"width":180,"source":"https:\/\/fbcdn-photos-d-a.akamaihd.net\/hphotos-ak-snc7\/392793_421104927976817_27125352_a.jpg"},{"height":130,"width":121,"source":"https:\/\/fbcdn-photos-d-a.akamaihd.net\/hphotos-ak-snc7\/392793_421104927976817_27125352_s.jpg"},{"height":130,"width":121,"source":"https:\/\/fbcdn-photos-d-a.akamaihd.net\/hphotos-ak-snc7\/s75x225\/392793_421104927976817_27125352_s.jpg"}],"link":"http:\/\/www.facebook.com\/photo.php?fbid=421104927976817&set=p.421104927976817&type=1","icon":"https:\/\/fbstatic-a.akamaihd.net\/rsrc.php\/v2\/yz\/r\/StEh3RhPvjk.gif","created_time":"2013-03-13T18:06:53+0000","updated_time":"2013-03-13T18:06:57+0000","comments":{"data":[{"id":"421104927976817_1008406","from":{"name":"MekhumIn CocaoZilla","id":"100002417843068"},"message":"Ty :)","can_remove":false,"created_time":"2013-03-15T09:50:32+0000","like_count":1,"user_likes":false}],"paging":{"cursors":{"after":"MQ==","before":"MQ=="},"next":"https:\/\/graph.facebook.com\/421104927976817\/comments?access_token=AAACEdEose0cBAMYosNuQgnCMBhgO4meNR3qH1cjXNhenSu6GRD6HiTa20OCYdbn297Lf2pZALjodgovOYrfZB0K5KvL0ONYoSHKuOldxmnwN01tZBh8&limit=25&after=MQ\u00253D\u00253D"}},"likes":{"data":[{"id":"100005184759779","name":"Alex Hyde Sobe"},{"id":"100000797003432","name":"Mark Jones"},{"id":"100002483061669","name":"Ajay Rathod"},{"id":"100005566744491","name":"Emptiness Bhagat"},{"id":"100003160334138","name":"Deepak Prajapati"},{"id":"100005311175891","name":"Shedup Lama"},{"id":"100004639656960","name":"Dazzling Nirav"},{"id":"100001205085426","name":"Sonam Rumba A"},{"id":"100002417843068","name":"MekhumIn CocaoZilla"},{"id":"100001714859224","name":"Choms Hyolmo"},{"id":"100004009380063","name":"Piter Toto"},{"id":"100001454818080","name":"Rinchen Namgyal"},{"id":"100005159641552","name":"Harry Tilala"},{"id":"100002158816738","name":"Neetu Raju"},{"id":"100002129702794","name":"SHivangi BHatt"},{"id":"100003922545347","name":"Ridham Sangani"},{"id":"100005078229824","name":"Eric Vance Cabling"},{"id":"100001820774634","name":"Faysal Mallick"},{"id":"100001474423074","name":"Pembob Thup"},{"id":"100003502740279","name":"Krishna Dholariya"},{"id":"100002498413595","name":"Ravi Patel"},{"id":"100002319395286","name":"Bhatt Suraj"}],"paging":{"next":"https:\/\/graph.facebook.com\/421104927976817\/likes?access_token=AAACEdEose0cBAMYosNuQgnCMBhgO4meNR3qH1cjXNhenSu6GRD6HiTa20OCYdbn297Lf2pZALjodgovOYrfZB0K5KvL0ONYoSHKuOldxmnwN01tZBh8&limit=25&offset=25&__after_id=100002319395286"}}},{"id":"122040707976755","from":{"name":"Christina Sutton","id":"100005124793318"},"name":"Sooo excited!!! New Monday night Partyyy! Lets go!!! \u2764 Tonight's gonna be a good night! MSG me if any questions","picture":"https:\/\/fbcdn-photos-a.akamaihd.net\/hphotos-ak-ash3\/556029_122040707976755_801283979_s.jpg","source":"https:\/\/fbcdn-sphotos-c-a.akamaihd.net\/hphotos-ak-ash3\/556029_122040707976755_801283979_n.jpg","height":513,"width":640,"images":[{"height":513,"width":640,"source":"https:\/\/fbcdn-sphotos-c-a.akamaihd.net\/hphotos-ak-ash3\/556029_122040707976755_801283979_n.jpg"},{"height":513,"width":640,"source":"https:\/\/fbcdn-sphotos-c-a.akamaihd.net\/hphotos-ak-ash3\/556029_122040707976755_801283979_n.jpg"},{"height":480,"width":600,"source":"https:\/\/fbcdn-sphotos-c-a.akamaihd.net\/hphotos-ak-ash3\/s600x600\/556029_122040707976755_801283979_n.jpg"},{"height":384,"width":480,"source":"https:\/\/fbcdn-sphotos-c-a.akamaihd.net\/hphotos-ak-ash3\/s480x480\/556029_122040707976755_801283979_n.jpg"},{"height":256,"width":320,"source":"https:\/\/fbcdn-sphotos-c-a.akamaihd.net\/hphotos-ak-ash3\/s320x320\/556029_122040707976755_801283979_n.jpg"},{"height":144,"width":180,"source":"https:\/\/fbcdn-photos-a.akamaihd.net\/hphotos-ak-ash3\/556029_122040707976755_801283979_a.jpg"},{"height":104,"width":130,"source":"https:\/\/fbcdn-photos-a.akamaihd.net\/hphotos-ak-ash3\/556029_122040707976755_801283979_s.jpg"},{"height":104,"width":130,"source":"https:\/\/fbcdn-photos-a.akamaihd.net\/hphotos-ak-ash3\/s75x225\/556029_122040707976755_801283979_s.jpg"}],"link":"http:\/\/www.facebook.com\/photo.php?fbid=122040707976755&set=p.122040707976755&type=1","icon":"https:\/\/fbstatic-a.akamaihd.net\/rsrc.php\/v2\/yz\/r\/StEh3RhPvjk.gif","created_time":"2013-02-19T02:13:21+0000","updated_time":"2013-02-19T02:15:32+0000","comments":{"data":[{"id":"122040707976755_31000","from":{"name":"Iliesha Taylor","id":"733495913"},"message":"was a truly awesum night!! can't wait for next week!!!","can_remove":false,"created_time":"2013-02-19T07:10:11+0000","like_count":1,"user_likes":false}],"paging":{"cursors":{"after":"MQ==","before":"MQ=="},"next":"https:\/\/graph.facebook.com\/122040707976755\/comments?access_token=AAACEdEose0cBAMYosNuQgnCMBhgO4meNR3qH1cjXNhenSu6GRD6HiTa20OCYdbn297Lf2pZALjodgovOYrfZB0K5KvL0ONYoSHKuOldxmnwN01tZBh8&limit=25&after=MQ\u00253D\u00253D"}},"likes":{"data":[{"id":"100000995140126","name":"Zachary Courtney"},{"id":"100004995005963","name":"Lenis Gonzalez"},{"id":"100001536197899","name":"Jaron Hamilton"},{"id":"100001591961112","name":"Elisabeth Depaula"}],"paging":{"next":"https:\/\/graph.facebook.com\/122040707976755\/likes?access_token=AAACEdEose0cBAMYosNuQgnCMBhgO4meNR3qH1cjXNhenSu6GRD6HiTa20OCYdbn297Lf2pZALjodgovOYrfZB0K5KvL0ONYoSHKuOldxmnwN01tZBh8&limit=25&offset=25&__after_id=100001591961112"}}},{"id":"122029301311229","from":{"name":"Christina Sutton","id":"100005124793318"},"name":"Super excited for tonight! New Monday party at Hyde Beach!!! Yay!!!\u2764\u2764","picture":"https:\/\/fbcdn-photos-g-a.akamaihd.net\/hphotos-ak-ash3\/521313_122029301311229_1375718944_s.jpg","source":"https:\/\/fbcdn-sphotos-g-a.akamaihd.net\/hphotos-ak-ash3\/521313_122029301311229_1375718944_n.jpg","height":513,"width":640,"images":[{"height":513,"width":640,"source":"https:\/\/fbcdn-sphotos-g-a.akamaihd.net\/hphotos-ak-ash3\/521313_122029301311229_1375718944_n.jpg"},{"height":513,"width":640,"source":"https:\/\/fbcdn-sphotos-g-a.akamaihd.net\/hphotos-ak-ash3\/521313_122029301311229_1375718944_n.jpg"},{"height":480,"width":600,"source":"https:\/\/fbcdn-sphotos-g-a.akamaihd.net\/hphotos-ak-ash3\/s600x600\/521313_122029301311229_1375718944_n.jpg"},{"height":384,"width":480,"source":"https:\/\/fbcdn-sphotos-g-a.akamaihd.net\/hphotos-ak-ash3\/s480x480\/521313_122029301311229_1375718944_n.jpg"},{"height":256,"width":320,"source":"https:\/\/fbcdn-sphotos-g-a.akamaihd.net\/hphotos-ak-ash3\/s320x320\/521313_122029301311229_1375718944_n.jpg"},{"height":144,"width":180,"source":"https:\/\/fbcdn-photos-g-a.akamaihd.net\/hphotos-ak-ash3\/521313_122029301311229_1375718944_a.jpg"},{"height":104,"width":130,"source":"https:\/\/fbcdn-photos-g-a.akamaihd.net\/hphotos-ak-ash3\/521313_122029301311229_1375718944_s.jpg"},{"height":104,"width":130,"source":"https:\/\/fbcdn-photos-g-a.akamaihd.net\/hphotos-ak-ash3\/s75x225\/521313_122029301311229_1375718944_s.jpg"}],"link":"http:\/\/www.facebook.com\/photo.php?fbid=122029301311229&set=p.122029301311229&type=1","icon":"https:\/\/fbstatic-a.akamaihd.net\/rsrc.php\/v2\/yz\/r\/StEh3RhPvjk.gif","created_time":"2013-02-19T01:17:32+0000","updated_time":"2013-02-19T01:18:10+0000","likes":{"data":[{"id":"578888215","name":"Justin Gary"},{"id":"1574121861","name":"Kristi Sander Ricks"},{"id":"10201800","name":"Zac Courtney"},{"id":"100005124793318","name":"Christina Sutton"}],"paging":{"next":"https:\/\/graph.facebook.com\/122029301311229\/likes?access_token=AAACEdEose0cBAMYosNuQgnCMBhgO4meNR3qH1cjXNhenSu6GRD6HiTa20OCYdbn297Lf2pZALjodgovOYrfZB0K5KvL0ONYoSHKuOldxmnwN01tZBh8&limit=25&offset=25&__after_id=100005124793318"}}}],"paging":{"previous":"https:\/\/graph.facebook.com\/100005184759779\/photos?access_token=AAACEdEose0cBAMYosNuQgnCMBhgO4meNR3qH1cjXNhenSu6GRD6HiTa20OCYdbn297Lf2pZALjodgovOYrfZB0K5KvL0ONYoSHKuOldxmnwN01tZBh8&limit=25&since=1366031871&__previous=1","next":"https:\/\/graph.facebook.com\/100005184759779\/photos?access_token=AAACEdEose0cBAMYosNuQgnCMBhgO4meNR3qH1cjXNhenSu6GRD6HiTa20OCYdbn297Lf2pZALjodgovOYrfZB0K5KvL0ONYoSHKuOldxmnwN01tZBh8&limit=25&until=1361236651"}}