{"data":[{"id":"267047876754684","from":{"name":"Milica Lazic","id":"100003484218116"},"name":"Untitled Album","link":"http:\/\/www.facebook.com\/album.php?fbid=267047876754684&id=100003484218116&aid=64701","cover_photo":"277852052340933","count":10,"type":"normal","created_time":"2012-12-28T17:17:48+0000","updated_time":"2013-01-20T19:59:38+0000","can_upload":false,"likes":{"data":[{"id":"100004424046278","name":"Karim Bouhelal"},{"id":"100001488569104","name":"Goran Miti\u0107"},{"id":"100004016449470","name":"Aleksandar Stankovic"},{"id":"100002922053012","name":"Dejan Stankovic"},{"id":"100001963504504","name":"Nikolic Misa"},{"id":"100003236936427","name":"Dragan Djordjevic"},{"id":"100001681247899","name":"Erdinc Bajramovic"},{"id":"100002365021936","name":"Juan Mauricio Rojas Zuluaga"},{"id":"100004598976990","name":"\u0627\u0645\u064a\u0631 \u0632\u0647\u0648\u0631"},{"id":"100000647864137","name":"Dimaz Dwi Sya'bandi"},{"id":"100002971318114","name":"Beyaz Leke"},{"id":"1047464713","name":"William Francisco Flores Reyes"},{"id":"100004240863659","name":"Vlado Arabadzic"},{"id":"100005100460797","name":"\u0639\u0627\u0632\u0641\u0629 \u0627\u0644\u0623\u0645\u0644"},{"id":"100004015472030","name":"Jose Dee Soldatii"},{"id":"100004972452088","name":"Tutankamon Tuta"},{"id":"100004503397193","name":"Ljiljana Blagojevi\u0107"},{"id":"1184501450","name":"Goran Mirkovski"},{"id":"100001268480823","name":"Mitja Perko"}],"paging":{"next":"https:\/\/graph.facebook.com\/267047876754684\/likes?access_token=AAACEdEose0cBAJW1StQUSMiKXKbxIni7CK836T2At8W8kZCLPPwZBdiZBS1ZBxiqDKiwhwPF6kLZCRwFccO1RHe1DhodHWddCIjG2TuWXucuHQL4JF96S&limit=25&offset=25&__after_id=100001268480823"}},"comments":{"data":[{"id":"267047876754684_1281351","from":{"name":"Dimaz Dwi Sya'bandi","id":"100000647864137"},"message":"nice","can_remove":false,"created_time":"2013-02-05T09:45:18+0000","like_count":0,"user_likes":false},{"id":"267047876754684_1324459","from":{"name":"Karim Bouhelal","id":"100004424046278"},"message":"you are beautiful","can_remove":false,"created_time":"2013-02-18T22:15:45+0000","like_count":0,"user_likes":false}],"paging":{"next":"https:\/\/graph.facebook.com\/267047876754684\/comments?access_token=AAACEdEose0cBAJW1StQUSMiKXKbxIni7CK836T2At8W8kZCLPPwZBdiZBS1ZBxiqDKiwhwPF6kLZCRwFccO1RHe1DhodHWddCIjG2TuWXucuHQL4JF96S&limit=25&offset=25&__after_id=267047876754684_1324459"}}},{"id":"161584143967725","from":{"name":"Milica Lazic","id":"100003484218116"},"name":"Cover Photos","link":"http:\/\/www.facebook.com\/album.php?fbid=161584143967725&id=100003484218116&aid=33156","cover_photo":"267053736754098","count":1,"type":"normal","created_time":"2012-04-21T17:38:24+0000","updated_time":"2012-12-28T17:38:12+0000","can_upload":false},{"id":"113598782099595","from":{"name":"Milica Lazic","id":"100003484218116"},"name":"Profile Pictures","link":"http:\/\/www.facebook.com\/album.php?fbid=113598782099595&id=100003484218116&aid=11225","cover_photo":"267048430087962","count":1,"type":"profile","created_time":"2012-02-15T19:06:42+0000","updated_time":"2012-12-28T17:19:37+0000","can_upload":false},{"id":"113602075432599","from":{"name":"Milica Lazic","id":"100003484218116"},"name":"Untitled Album","link":"http:\/\/www.facebook.com\/album.php?fbid=113602075432599&id=100003484218116&aid=11226","type":"normal","created_time":"2012-02-15T19:11:12+0000","updated_time":"2012-12-28T16:37:29+0000","can_upload":false,"likes":{"data":[{"id":"100002239451258","name":"Sanja Peric"}],"paging":{"next":"https:\/\/graph.facebook.com\/113602075432599\/likes?access_token=AAACEdEose0cBAJW1StQUSMiKXKbxIni7CK836T2At8W8kZCLPPwZBdiZBS1ZBxiqDKiwhwPF6kLZCRwFccO1RHe1DhodHWddCIjG2TuWXucuHQL4JF96S&limit=25&offset=25&__after_id=100002239451258"}}}]}