{"data":[{"id":"145471485602185","from":{"name":"Liz Montgomery","id":"100004180028317"},"name":"Timeline Photos","link":"http:\/\/www.facebook.com\/album.php?fbid=145471485602185&id=100004180028317&aid=32988","cover_photo":"145471002268900","count":3,"type":"wall","created_time":"2012-12-27T09:04:00+0000","updated_time":"2013-02-16T07:34:32+0000","can_upload":false},{"id":"106848299464504","from":{"name":"Liz Montgomery","id":"100004180028317"},"name":"Cover Photos","link":"http:\/\/www.facebook.com\/album.php?fbid=106848299464504&id=100004180028317&aid=17121","cover_photo":"106848302797837","count":1,"type":"normal","created_time":"2012-08-22T14:20:42+0000","updated_time":"2012-08-22T14:20:48+0000","can_upload":false},{"id":"106841796131821","from":{"name":"Liz Montgomery","id":"100004180028317"},"name":"Profile Pictures","link":"http:\/\/www.facebook.com\/album.php?fbid=106841796131821&id=100004180028317&aid=17104","cover_photo":"106841959465138","count":1,"type":"profile","created_time":"2012-08-22T14:07:33+0000","updated_time":"2012-08-22T14:07:57+0000","can_upload":false}],"paging":{"cursors":{"after":"MTA2ODQxNzk2MTMxODIx","before":"MTQ1NDcxNDg1NjAyMTg1"}}}